utils/__init__.py
utils/dateutil.py
winkfin-0.0.2.dist-info/LICENSE.txt
winkfin-0.0.2.dist-info/METADATA
winkfin-0.0.2.dist-info/WHEEL
winkfin-0.0.2.dist-info/top_level.txt
winkfin-0.0.2.dist-info/RECORD
