Metadata-Version: 2.1
Name: winkfin
Version: 0.0.2
Summary: Winkstone Finance Utility Package
Home-page: https://github.com/winkstone
Author: winkstone
Author-email: hslee@winkstone.com
License: UNKNOWN
Platform: UNKNOWN
Classifier: Programming Language :: Python :: 3
Classifier: License :: OSI Approved :: MIT License
Classifier: Operating System :: OS Independent
